inception_fid_weights_zst_shard02/__init__.py
inception_fid_weights_zst_shard02/data/shard-02.bin
inception_fid_weights_zst_shard02-0.1.0.dist-info/METADATA
inception_fid_weights_zst_shard02-0.1.0.dist-info/WHEEL
inception_fid_weights_zst_shard02-0.1.0.dist-info/top_level.txt
inception_fid_weights_zst_shard02-0.1.0.dist-info/RECORD
