Metadata-Version: 2.4
Name: inception-fid-weights-zst-shard02
Version: 0.1.0
Summary: Shard 02 for inception-fid-weights-zst
Author: Your Name
Requires-Python: >=3.8
